geoai/__init__.py
geoai/auto.py
geoai/change_detection.py
geoai/classify.py
geoai/detectron2.py
geoai/dinov3.py
geoai/download.py
geoai/extract.py
geoai/geoai.py
geoai/hf.py
geoai/landcover_train.py
geoai/landcover_utils.py
geoai/map_widgets.py
geoai/moondream.py
geoai/prithvi.py
geoai/sam.py
geoai/segment.py
geoai/segmentation.py
geoai/timm_regress.py
geoai/timm_segment.py
geoai/timm_train.py
geoai/train.py
geoai/utils.py
geoai/agents/__init__.py
geoai/agents/catalog_models.py
geoai/agents/catalog_tools.py
geoai/agents/geo_agents.py
geoai/agents/map_tools.py
geoai/agents/stac_models.py
geoai/agents/stac_tools.py
geoai/tools/__init__.py
geoai/tools/cloudmask.py
geoai/tools/multiclean.py
geoai/tools/sr.py
geoai_py-0.27.0.dist-info/licenses/LICENSE
geoai_py-0.27.0.dist-info/METADATA
geoai_py-0.27.0.dist-info/WHEEL
geoai_py-0.27.0.dist-info/entry_points.txt
geoai_py-0.27.0.dist-info/top_level.txt
geoai_py-0.27.0.dist-info/RECORD
