Metadata-Version: 2.4
Name: geoai-py
Version: 0.27.0
Summary: A Python package for using Artificial Intelligence (AI) with geospatial data
Author-email: Qiusheng Wu <giswqs@gmail.com>
License: MIT License
Project-URL: Homepage, https://github.com/opengeos/geoai
Keywords: geoai
Classifier: Intended Audience :: Developers
Classifier: License :: OSI Approved :: MIT License
Classifier: Natural Language :: English
Classifier: Programming Language :: Python :: 3.10
Classifier: Programming Language :: Python :: 3.11
Classifier: Programming Language :: Python :: 3.12
Classifier: Programming Language :: Python :: 3.13
Requires-Python: >=3.10
License-File: LICENSE
Requires-Dist: albumentations
Requires-Dist: buildingregulariser
Requires-Dist: contextily
Requires-Dist: datasets>=3.0
Requires-Dist: ever-beta
Requires-Dist: geopandas
Requires-Dist: huggingface_hub
Requires-Dist: jupyter-server-proxy
Requires-Dist: leafmap>=0.57.1
Requires-Dist: localtileserver
Requires-Dist: mapclassify
Requires-Dist: maplibre
Requires-Dist: opencv-python-headless
Requires-Dist: overturemaps
Requires-Dist: planetary-computer
Requires-Dist: psutil
Requires-Dist: pyarrow
Requires-Dist: pystac-client
Requires-Dist: rasterio
Requires-Dist: rioxarray
Requires-Dist: scikit-image
Requires-Dist: scikit-learn
Requires-Dist: smoothify
Requires-Dist: timm
Requires-Dist: tokenizers>=0.22.1
Requires-Dist: torch
Requires-Dist: torchgeo
Requires-Dist: torchinfo
Requires-Dist: tqdm
Requires-Dist: transformers>=4.57.1
Provides-Extra: extra
Requires-Dist: overturemaps; extra == "extra"
Requires-Dist: torchange; extra == "extra"
Requires-Dist: lightly-train; extra == "extra"
Requires-Dist: multiclean; extra == "extra"
Requires-Dist: omnicloudmask; extra == "extra"
Requires-Dist: smoothify; extra == "extra"
Provides-Extra: agents
Requires-Dist: strands-agents; extra == "agents"
Requires-Dist: strands-agents-tools; extra == "agents"
Requires-Dist: strands-agents[ollama]; extra == "agents"
Requires-Dist: strands-agents[anthropic]; extra == "agents"
Requires-Dist: strands-agents[openai]; extra == "agents"
Provides-Extra: sr
Requires-Dist: opensr-model; extra == "sr"
Dynamic: license-file
